parcadfc/__init__.py
parcadfc/parcadfc.py
parcadfc/parcadfc_aux.py
parcadfc/paux_material/templateCover.docx
parcadfc/paux_material/templateRec.docx
parcadfc/paux_material/images/critical
parcadfc/paux_material/images/high
parcadfc/paux_material/images/low
parcadfc/paux_material/images/medium
parcadfc-1.0.8.dist-info/METADATA
parcadfc-1.0.8.dist-info/WHEEL
parcadfc-1.0.8.dist-info/top_level.txt
parcadfc-1.0.8.dist-info/RECORD
